README.md
setup.cfg
setup.py
TheAlgorithms_pkg_YOUR_USERNAME_HERE.egg-info/PKG-INFO
TheAlgorithms_pkg_YOUR_USERNAME_HERE.egg-info/SOURCES.txt
TheAlgorithms_pkg_YOUR_USERNAME_HERE.egg-info/dependency_links.txt
TheAlgorithms_pkg_YOUR_USERNAME_HERE.egg-info/requires.txt
TheAlgorithms_pkg_YOUR_USERNAME_HERE.egg-info/top_level.txt
TheAlgoritms_pkg/__init__.py
TheAlgoritms_pkg/autokey_cipher.py
TheAlgoritms_pkg/caesar_cipher.py
TheAlgoritms_pkg/vigenere_cipher.py
TheAlgoritms_pkg/xor_cipher.py